animegirlapi/__init__.py
animegirlapi/main.py
animegirlapi-1.6.0.dist-info/METADATA
animegirlapi-1.6.0.dist-info/WHEEL
animegirlapi-1.6.0.dist-info/top_level.txt
animegirlapi-1.6.0.dist-info/RECORD
