Metadata-Version: 2.1
Name: animegirlapi
Version: 1.6.0
Summary: An API that can output anime girls, and is 100% manually verified
Author: Alleexx
Author-email: Alleexx129@gmail.com
Classifier: Programming Language :: Python :: 3
Classifier: License :: OSI Approved :: MIT License
Classifier: Operating System :: OS Independent
Requires-Dist: requests>=2.25.1
